dilimap/__init__.py
dilimap/_version.py
dilimap/clients.py
dilimap/datasets.py
dilimap/logging.py
dilimap/models.py
dilimap/plotting.py
dilimap/preprocessing.py
dilimap/s3.py
dilimap/utils.py
dilimap/deseq2/.config.vsh.yaml
dilimap/deseq2/deseq_exec
dilimap/deseq2/deseq_pert.py
dilimap-1.0.5.dist-info/METADATA
dilimap-1.0.5.dist-info/WHEEL
dilimap-1.0.5.dist-info/licenses/LICENSE
dilimap-1.0.5.dist-info/RECORD
