Metadata-Version: 2.4
Name: DILImap
Version: 1.0.5
Author-email: Volker Bergen <vbergen@cellarity.com>
License-File: LICENSE
Classifier: License :: Other/Proprietary License
Requires-Python: >=3.8
Requires-Dist: anndata>=0.10.7
Requires-Dist: boto3
Requires-Dist: chembl-webresource-client
Requires-Dist: dask
Requires-Dist: distributed
Requires-Dist: matplotlib
Requires-Dist: natsort
Requires-Dist: numpy>1.25
Requires-Dist: pandas
Requires-Dist: python-dotenv
Requires-Dist: quilt3
Requires-Dist: scikit-learn<2.0.0,>=1.4.0
Requires-Dist: scipy
Requires-Dist: seaborn
Provides-Extra: build
Requires-Dist: build; extra == 'build'
Requires-Dist: twine; extra == 'build'
Provides-Extra: dev
Requires-Dist: pre-commit; extra == 'dev'
Requires-Dist: ruff; extra == 'dev'
Provides-Extra: doc
Requires-Dist: ipykernel; extra == 'doc'
Requires-Dist: nbclean; extra == 'doc'
Requires-Dist: nbconvert; extra == 'doc'
Requires-Dist: nbsphinx; extra == 'doc'
Requires-Dist: pygments; extra == 'doc'
Requires-Dist: readthedocs-sphinx-search; extra == 'doc'
Requires-Dist: sphinx-autodoc-typehints; extra == 'doc'
Requires-Dist: sphinx-jinja; extra == 'doc'
Requires-Dist: sphinx-rtd-theme; extra == 'doc'
Requires-Dist: sphinx<7; extra == 'doc'
Provides-Extra: test
Requires-Dist: black; extra == 'test'
Requires-Dist: flake8; extra == 'test'
Requires-Dist: pyflakes; extra == 'test'
Requires-Dist: pytest; extra == 'test'
Requires-Dist: pytest-cov; extra == 'test'
